json_logify-0.1.2.dist-info/licenses/LICENSE
logify/__init__.py
logify/core.py
logify/django.py
logify/fastapi.py
logify/flask.py
logify/version.py
json_logify-0.1.2.dist-info/METADATA
json_logify-0.1.2.dist-info/WHEEL
json_logify-0.1.2.dist-info/top_level.txt
json_logify-0.1.2.dist-info/RECORD
