Metadata-Version: 2.4
Name: json-logify
Version: 0.1.2
Summary: Universal structured logging with exact JSON schema for Python frameworks
Author-email: Bakdoolot Kulbarakov <kulbarakovbh@gmail.com>
Maintainer-email: Bakdoolot Kulbarakov <kulbarakovbh@gmail.com>
License: MIT License
Project-URL: Homepage, https://github.com/yourusername/json-logify
Project-URL: Documentation, https://json-logify.readthedocs.io/
Project-URL: Repository, https://github.com/yourusername/json-logify
Project-URL: Issues, https://github.com/yourusername/json-logify/issues
Project-URL: Changelog, https://github.com/yourusername/json-logify/blob/main/CHANGELOG.md
Keywords: logging,structured,json,django,fastapi,flask,universal,schema,orjson,structlog
Classifier: Development Status :: 5 - Production/Stable
Classifier: Intended Audience :: Developers
Classifier: License :: OSI Approved :: MIT License
Classifier: Operating System :: OS Independent
Classifier: Programming Language :: Python :: 3
Classifier: Programming Language :: Python :: 3.8
Classifier: Programming Language :: Python :: 3.9
Classifier: Programming Language :: Python :: 3.10
Classifier: Programming Language :: Python :: 3.11
Classifier: Programming Language :: Python :: 3.12
Classifier: Topic :: Software Development :: Libraries :: Python Modules
Classifier: Topic :: System :: Logging
Classifier: Framework :: Django
Classifier: Framework :: FastAPI
Classifier: Framework :: Flask
Requires-Python: >=3.12
License-File: LICENSE
Requires-Dist: structlog>=23.0.0
Requires-Dist: orjson>=3.8.0
Provides-Extra: django
Requires-Dist: django>=5.2.6; extra == "django"
Provides-Extra: dev
Requires-Dist: pytest>=8.4.2; extra == "dev"
Requires-Dist: pytest-cov>=4.0.0; extra == "dev"
Requires-Dist: pytest-asyncio>=0.21.0; extra == "dev"
Requires-Dist: black>=23.0.0; extra == "dev"
Requires-Dist: isort>=5.12.0; extra == "dev"
Requires-Dist: flake8>=6.0.0; extra == "dev"
Requires-Dist: mypy>=1.0.0; extra == "dev"
Requires-Dist: pre-commit>=3.0.0; extra == "dev"
Requires-Dist: bandit>=1.7.5; extra == "dev"
Provides-Extra: all
Requires-Dist: json-logify[django,fastapi,flask]; extra == "all"
Dynamic: license-file
